<?xml version="1.0" encoding="ISO-8859-1"?>
<message_catalog package_key="search" locale="es_ES" charset="ISO-8859-1">

  <msg key="________Search_took">. Búsqueda tardo</msg>
  <msg key="Advanced_Search">Búsqueda Avanzada</msg>
  <msg key="advanced_search">&#34;búsqueda avanzada&#34;</msg>
  <msg key="anytime">cualquier hora</msg>
  <msg key="Date_Range">Rango de Fechas</msg>
  <msg key="details">detalles</msg>
  <msg key="Enter_keywords_to_search_for">Introducir palabras a buscar</msg>
  <msg key="Feeling_Lucky">Me siento afortunado</msg>
  <msg key="lt_bstopwordsb_is_a_very">&#34;&lt;b&gt;%stopwords%&lt;/b&gt;&#34; es una palabra muy común y no ha sido tomada en cuenta para la búsqueda.</msg>
  <msg key="lt_FtsEngineDriver_not_a">¡FtsEngineDriver no disponible!</msg>
  <msg key="lt_Make_sure_all_words_a">Asegúrese que todas las palabras estén escritas correctamente.</msg>
  <msg key="lt_No_pages_were_found_c">No se ha encontrado páginas que contengan &#34;</msg>
  <msg key="lt_The_following_words_a">Las palabras siguientes son demasiado comunes y no han sido incluidas en su búsqueda:</msg>
  <msg key="lt_Tip_In_most_browsers_">Consejo: En la mayoría de los navegadores, puede pulsar la tecla Intro en lugar de pulsar el botón de búsqueda</msg>
  <msg key="lt_Try_different_keyword">Inténtelo con otras palabras.</msg>
  <msg key="lt_Try_more_general_keyw">Inténtelo con palabras más genéricas.</msg>
  <msg key="lt_Try_your_query_on_stw">Intente realizar la búsqueda sobre %stw;noquote%</msg>
  <msg key="lt_You_must_specify_some">Debe especificar algunas palabras.</msg>
  <msg key="nbspDisplay">&amp;nbsp;Mostrar</msg>
  <msg key="Next">Siguiente</msg>
  <msg key="of_about">de</msg>
  <msg key="past_3_months">últimos 3 meses</msg>
  <msg key="past_6_months">últimos 6 meses</msg>
  <msg key="past_year">año anterior</msg>
  <msg key="Previous">Anterior</msg>
  <msg key="Result_page">Página de resultados:</msg>
  <msg key="Results">Resultados</msg>
  <msg key="results">resultados</msg>
  <msg key="Search">Buscar</msg>
  <msg key="Searched_for_query">Búsquedas para: &lt;b&gt;%query%&lt;/b&gt;</msg>
  <msg key="seconds">segundos.</msg>
  <msg key="selected">seleccionado</msg>
  <msg key="Suggestions">Sugerencias:</msg>
  <msg key="The">El operador &#34;&lt;b&gt;AND&lt;/b&gt;&#34; no es necesario  -- por defecto, se incluyen todos los términos en la búsqueda.</msg>
  <msg key="Try_fewer_keywords">Inténtelo con más palabras.</msg>
  <msg key="Untitled">Sin título</msg>
</message_catalog>
