<?xml version="1.0" encoding="utf-8"?>
<message_catalog package_key="notifications" locale="fi_FI" charset="utf-8">

  <msg key="Action">Ilmoitustapa</msg>
  <msg key="Change">Muokkaa</msg>
  <msg key="Delivery_Method">Yhteydenottotapa</msg>
  <msg key="Frequency">Uusien ilmoitusten lähetystiheys</msg>
  <msg key="Item">Ilmoitus</msg>
  <msg key="lt_Getting_too_much_emai">Tulviiko postilaatikkosi? Muokkaa muistutusasetuksiasi: %manage_notifications_url%</msg>
  <msg key="lt_Notification_Interval">Muistutusten tiheys</msg>
  <msg key="lt_Request_Notification_">Haluan saada muistutuksen, kun %pretty_name% päivittyy</msg>
  <msg key="lt_system_name_-_Batched">[%system_name% - Erä uusia viestejä] </msg>
  <msg key="lt_You_have_no_notificat">Sinulla ei ole käytössä yhtään ilmoituspalvelua.</msg>
  <msg key="lt_You_have_requested_no">Olet pyytänyt saada ilmoituksen uusista viesteistä ryhmässä %pretty_name%. Halutessasi voit &lt;a href=&quot;%sub_url%&quot;&gt;peruuttaa ilmoituspalvelun&lt;/a&gt;.</msg>
  <msg key="Manage_Notifications">Muokkaa ilmoituksia</msg>
  <msg key="Notification_type">Ilmoituksen tyyppi</msg>
  <msg key="Request_Notification">Tilaa ilmoitus</msg>
  <msg key="SUBJECT">AIHE:</msg>
  <msg key="Unsubscribe">Peruuta ilmoituspalvelu</msg>
</message_catalog>
